README.md
setup.py
Fifteen_Puzzle_Game.egg-info/PKG-INFO
Fifteen_Puzzle_Game.egg-info/SOURCES.txt
Fifteen_Puzzle_Game.egg-info/dependency_links.txt
Fifteen_Puzzle_Game.egg-info/requires.txt
Fifteen_Puzzle_Game.egg-info/top_level.txt
Game/__init__.py
Game/main.py