Metadata-Version: 1.1
Name: Fifteen-Puzzle-Game
Version: 0.0.1
Summary: A Simple Puzzle Game
Home-page: https://github.com/skdhell/Fifteen-Puzzle-Game
Author: ShashiKant Dwivedi
Author-email: raghoram2009@gmail.com
License: MIT
Keywords: Solving Puzzle
Platform: UNKNOWN
Classifier: Development Status :: 4 - Beta
Classifier: Intended Audience :: Developers
Classifier: Topic :: Internet
Classifier: License :: OSI Approved :: MIT License
Classifier: Programming Language :: Python
Classifier: Programming Language :: Python :: 2
Classifier: Programming Language :: Python :: 2.6
Classifier: Programming Language :: Python :: 2.7
Classifier: Programming Language :: Python :: 3
Classifier: Programming Language :: Python :: 3.3
Classifier: Programming Language :: Python :: 3.4
Classifier: Programming Language :: Python :: 3.5
Classifier: Programming Language :: Python :: 3.6
